freeGPT/__init__.py
freeGPT/Client/__init__.py
freeGPT/Client/gpt3.py
freeGPT/Client/gpt3_5.py
freeGPT/Client/gpt4.py
freeGPT/Client/pollinations.py
freeGPT/Client/prodia.py
freeGPT-1.3.5.dist-info/LICENSE
freeGPT-1.3.5.dist-info/METADATA
freeGPT-1.3.5.dist-info/WHEEL
freeGPT-1.3.5.dist-info/top_level.txt
freeGPT-1.3.5.dist-info/RECORD
